MANIFEST.in
README.rst
setup.py
Confopy_webapp.egg-info/PKG-INFO
Confopy_webapp.egg-info/SOURCES.txt
Confopy_webapp.egg-info/dependency_links.txt
Confopy_webapp.egg-info/requires.txt
Confopy_webapp.egg-info/top_level.txt
confopyapp/__init__.py
confopyapp/app.py
confopyapp/templates/evaluate.html