Metadata-Version: 1.0
Name: Confopy-webapp
Version: 0.1.6.3
Summary: Minimal web UI for Confopy.
Home-page: https://github.com/ooz/Confopy-webapp
Author: Oliver Zscheyge
Author-email: oliverzscheyge@gmail.com
License: MIT
Platform: UNKNOWN
